{
  "tasks": [
    {
      "title": "lorem ipsum dolor",
      "complete": true,
      "id": 1
    },
    {
      "title": "sit amet",
      "complete": true,
      "id": 2
    },
    {
      "title": "dolor ipsum lorem",
      "complete": false,
      "id": 3
    },
    {
      "title": "random text",
      "complete": false,
      "id": 4
    },
    {
      "title": "koonk",
      "complete": true,
      "id": 6
    },
    {
      "title": "qwe2",
      "complete": false,
      "id": 8
    }
  ]
}